pandas_show/__init__.py
pandas_show/_nbdev.py
pandas_show/core.py
pandas_show-0.0.1.dist-info/LICENSE
pandas_show-0.0.1.dist-info/METADATA
pandas_show-0.0.1.dist-info/WHEEL
pandas_show-0.0.1.dist-info/entry_points.txt
pandas_show-0.0.1.dist-info/top_level.txt
pandas_show-0.0.1.dist-info/RECORD
